OrangeLab/__init__.py
OrangeLab/fake.py
OrangeLab/image.py
OrangeLab/init_file.py
OrangeLab-0.0.1.dist-info/LICENCE.txt
OrangeLab-0.0.1.dist-info/METADATA
OrangeLab-0.0.1.dist-info/WHEEL
OrangeLab-0.0.1.dist-info/top_level.txt
OrangeLab-0.0.1.dist-info/RECORD
