Metadata-Version: 2.1
Name: OrangeLab
Version: 0.0.1
Summary: The Python module developed for the Orange Python Tool Plugin serves a dual purpose, providing functionalities for both image processing using OpenCV and the generation of synthetic datasets through the Faker library.
Home-page: https://www.pythonanywhere.com/
Author: NagiPragalathan
Author-email: nagipragalathan@gmail.com
License: MIT
Keywords: Image Processing,Computer Vision,Color Analysis,Color Design,Color Palette,Image Enhancement,Image Filters,Feature Extraction,Pattern Recognition,Color Manipulation,Image Segmentation,Color Spaces,Histogram Equalization,Edge Detection,Contrast Adjustment,Saturation Control,Hue Adjustment,Color Grading,Image Restoration,Color Correction,Digital Image Processing,Visual Perception,Color Harmony,Color Psychology,Image Effects,Texture Synthesis,Color Transfer,Image Compression,Color Quantiz
Classifier: Development Status :: 5 - Production/Stable
Classifier: Intended Audience :: Education
Classifier: Operating System :: Microsoft :: Windows :: Windows 10
Classifier: License :: OSI Approved :: MIT License
Classifier: Programming Language :: Python :: 3
License-File: LICENCE.txt
Requires-Dist: numpy >=1.18.0
Requires-Dist: opencv-python >=4.2.0
Requires-Dist: matplotlib >=3.1.0
Requires-Dist: Faker >=8.14.0
Requires-Dist: Pillow >=8.2.0
Requires-Dist: pandas >=1.0.0
